tauth/__init__.py
tauth/__main__.py
tauth/app.py
tauth/settings.py
tauth/authn/__init__.py
tauth/authn/authenticator.py
tauth/authn/routes.py
tauth/authn/utils.py
tauth/authn/jwt/__init__.py
tauth/authn/jwt/constants.py
tauth/authn/jwt/credentials.py
tauth/authn/jwt/errors.py
tauth/authn/jwt/keygen.py
tauth/authn/jwt/tokcoder.py
tauth/authn/melt_key/README.md
tauth/authn/melt_key/__init__.py
tauth/authn/melt_key/authentication.py
tauth/authn/melt_key/authorization.py
tauth/authn/melt_key/models.py
tauth/authn/melt_key/schemas.py
tauth/authn/melt_key/token.py
tauth/authn/oauth2/__init__.py
tauth/authn/oauth2/authentication.py
tauth/authn/oauth2/models.py
tauth/authn/oauth2/schemas.py
tauth/authn/oauth2/utils.py
tauth/authn/remote/__init__.py
tauth/authn/remote/engine.py
tauth/authn/remote/settings.py
tauth/authn/tauth_keys/__init__.py
tauth/authn/tauth_keys/authentication.py
tauth/authn/tauth_keys/keygen.py
tauth/authn/tauth_keys/models.py
tauth/authn/tauth_keys/schemas.py
tauth/authn/tauth_keys/utils.py
tauth/authproviders/__init__.py
tauth/authproviders/models.py
tauth/authproviders/routes.py
tauth/authproviders/schemas.py
tauth/authz/__init__.py
tauth/authz/controllers.py
tauth/authz/privileges.py
tauth/authz/routes.py
tauth/authz/utils.py
tauth/authz/engines/__init__.py
tauth/authz/engines/errors.py
tauth/authz/engines/factory.py
tauth/authz/engines/interface.py
tauth/authz/engines/opa/__init__.py
tauth/authz/engines/opa/engine.py
tauth/authz/engines/opa/settings.py
tauth/authz/engines/remote/__init__.py
tauth/authz/engines/remote/engine.py
tauth/authz/engines/remote/settings.py
tauth/authz/permissions/__init__.py
tauth/authz/permissions/controllers.py
tauth/authz/permissions/models.py
tauth/authz/permissions/routes.py
tauth/authz/permissions/schemas.py
tauth/authz/policies/__init__.py
tauth/authz/policies/controllers.py
tauth/authz/policies/models.py
tauth/authz/policies/routes.py
tauth/authz/policies/schemas.py
tauth/authz/roles/__init__.py
tauth-2.9.0.dist-info/licenses/LICENSE
tauth-2.9.0.dist-info/METADATA
tauth-2.9.0.dist-info/WHEEL
tauth-2.9.0.dist-info/top_level.txt
tauth-2.9.0.dist-info/RECORD
